<map>  
<county>
 <id>1</id>
 <name>Adams</name>
 <URL>#</URL>
 <popup>Any text &lt;BR&gt;information</popup>
 <color1>7798BA</color1>
 <color2>366CA3</color2>
</county>
<county>
 <id>2</id>
 <name>Ashland</name>
 <URL>#</URL>
 <popup>Any text &lt;BR&gt;information</popup>
 <color1>7798BA</color1>
 <color2>366CA3</color2>
</county>
<county>
 <id>3</id>
 <name>Barron</name>
 <URL>#</URL>
 <popup>Any text &lt;BR&gt;information</popup>
 <color1>7798BA</color1>
 <color2>366CA3</color2>
</county>
<county>
 <id>4</id>
 <name>Bayfield</name>
 <URL>#</URL>
 <popup>Any text &lt;BR&gt;information</popup>
 <color1>7798BA</color1>
 <color2>366CA3</color2>
</county>
<county>
 <id>5</id>
 <name>Brown</name>
 <URL>#</URL>
 <popup>Any text &lt;BR&gt;information</popup>
 <color1>7798BA</color1>
 <color2>366CA3</color2>
</county>
<county>
 <id>6</id>
 <name>Buffalo</name>
 <URL>#</URL>
 <popup>Any text &lt;BR&gt;information</popup>
 <color1>7798BA</color1>
 <color2>366CA3</color2>
</county>
<county>
 <id>7</id>
 <name>Burnett</name>
 <URL>#</URL>
 <popup>Any text &lt;BR&gt;information</popup>
 <color1>7798BA</color1>
 <color2>366CA3</color2>
</county>
<county>
 <id>8</id>
 <name>Calumet</name>
 <URL>#</URL>
 <popup>Any text &lt;BR&gt;information</popup>
 <color1>7798BA</color1>
 <color2>366CA3</color2>
</county>
<county>
 <id>9</id>
 <name>Chippewa</name>
 <URL>#</URL>
 <popup>Any text &lt;BR&gt;information</popup>
 <color1>7798BA</color1>
 <color2>366CA3</color2>
</county>
<county>
 <id>10</id>
 <name>Clark</name>
 <URL>#</URL>
 <popup>Any text &lt;BR&gt;information</popup>
 <color1>7798BA</color1>
 <color2>366CA3</color2>
</county>
<county>
 <id>11</id>
 <name>Columbia</name>
 <URL>#</URL>
 <popup>Any text &lt;BR&gt;information</popup>
 <color1>7798BA</color1>
 <color2>366CA3</color2>
</county>
<county>
 <id>12</id>
 <name>Crawford</name>
 <URL>#</URL>
 <popup>Any text &lt;BR&gt;information</popup>
 <color1>7798BA</color1>
 <color2>366CA3</color2>
</county>
<county>
 <id>13</id>
 <name>Dane</name>
 <URL>#</URL>
 <popup>Any text &lt;BR&gt;information</popup>
 <color1>7798BA</color1>
 <color2>366CA3</color2>
</county>
<county>
 <id>14</id>
 <name>Dodge</name>
 <URL>#</URL>
 <popup>Any text &lt;BR&gt;information</popup>
 <color1>7798BA</color1>
 <color2>366CA3</color2>
</county>
<county>
 <id>15</id>
 <name>Door</name>
 <URL>#</URL>
 <popup>Any text &lt;BR&gt;information</popup>
 <color1>7798BA</color1>
 <color2>366CA3</color2>
</county>
<county>
 <id>16</id>
 <name>Douglas</name>
 <URL>#</URL>
 <popup>Any text &lt;BR&gt;information</popup>
 <color1>7798BA</color1>
 <color2>366CA3</color2>
</county>
<county>
 <id>17</id>
 <name>Dunn</name>
 <URL>#</URL>
 <popup>Any text &lt;BR&gt;information</popup>
 <color1>7798BA</color1>
 <color2>366CA3</color2>
</county>
<county>
 <id>18</id>
 <name>Eau Claire</name>
 <URL>#</URL>
 <popup>Any text &lt;BR&gt;information</popup>
 <color1>7798BA</color1>
 <color2>366CA3</color2>
</county>
<county>
 <id>19</id>
 <name>Florence</name>
 <URL>#</URL>
 <popup>Any text &lt;BR&gt;information</popup>
 <color1>7798BA</color1>
 <color2>366CA3</color2>
</county>
<county>
 <id>20</id>
 <name>Fond du Lac</name>
 <URL>#</URL>
 <popup>Any text &lt;BR&gt;information</popup>
 <color1>7798BA</color1>
 <color2>366CA3</color2>
</county>
<county>
 <id>21</id>
 <name>Forest</name>
 <URL>#</URL>
 <popup>Any text &lt;BR&gt;information</popup>
 <color1>7798BA</color1>
 <color2>366CA3</color2>
</county>
<county>
 <id>22</id>
 <name>Grant</name>
 <URL>#</URL>
 <popup>Any text &lt;BR&gt;information</popup>
 <color1>7798BA</color1>
 <color2>366CA3</color2>
</county>
<county>
 <id>23</id>
 <name>Green</name>
 <URL>#</URL>
 <popup>Any text &lt;BR&gt;information</popup>
 <color1>7798BA</color1>
 <color2>366CA3</color2>
</county>
<county>
 <id>24</id>
 <name>Green Lake</name>
 <URL>#</URL>
 <popup>Any text &lt;BR&gt;information</popup>
 <color1>7798BA</color1>
 <color2>366CA3</color2>
</county>
<county>
 <id>25</id>
 <name>Iowa</name>
 <URL>#</URL>
 <popup>Any text &lt;BR&gt;information</popup>
 <color1>7798BA</color1>
 <color2>366CA3</color2>
</county>
<county>
 <id>26</id>
 <name>Iron</name>
 <URL>#</URL>
 <popup>Any text &lt;BR&gt;information</popup>
 <color1>7798BA</color1>
 <color2>366CA3</color2>
</county>
<county>
 <id>27</id>
 <name>Jackson</name>
 <URL>#</URL>
 <popup>Any text &lt;BR&gt;information</popup>
 <color1>7798BA</color1>
 <color2>366CA3</color2>
</county>
<county>
 <id>28</id>
 <name>Jefferson</name>
 <URL>#</URL>
 <popup>Any text &lt;BR&gt;information</popup>
 <color1>7798BA</color1>
 <color2>366CA3</color2>
</county>
<county>
 <id>29</id>
 <name>Juneau</name>
 <URL>#</URL>
 <popup>Any text &lt;BR&gt;information</popup>
 <color1>7798BA</color1>
 <color2>366CA3</color2>
</county>
<county>
 <id>30</id>
 <name>Kenosha</name>
 <URL>#</URL>
 <popup>Any text &lt;BR&gt;information</popup>
 <color1>7798BA</color1>
 <color2>366CA3</color2>
</county>
<county>
 <id>31</id>
 <name>Kewaunee</name>
 <URL>#</URL>
 <popup>Any text &lt;BR&gt;information</popup>
 <color1>7798BA</color1>
 <color2>366CA3</color2>
</county>
<county>
 <id>32</id>
 <name>La Crosse</name>
 <URL>#</URL>
 <popup>Any text &lt;BR&gt;information</popup>
 <color1>7798BA</color1>
 <color2>366CA3</color2>
</county>
<county>
 <id>33</id>
 <name>Lafayette</name>
 <URL>#</URL>
 <popup>Any text &lt;BR&gt;information</popup>
 <color1>7798BA</color1>
 <color2>366CA3</color2>
</county>
<county>
 <id>34</id>
 <name>Langlade</name>
 <URL>#</URL>
 <popup>Any text &lt;BR&gt;information</popup>
 <color1>7798BA</color1>
 <color2>366CA3</color2>
</county>
<county>
 <id>35</id>
 <name>Lincoln</name>
 <URL>#</URL>
 <popup>Any text &lt;BR&gt;information</popup>
 <color1>7798BA</color1>
 <color2>366CA3</color2>
</county>
<county>
 <id>36</id>
 <name>Manitowoc</name>
 <URL>#</URL>
 <popup>Any text &lt;BR&gt;information</popup>
 <color1>7798BA</color1>
 <color2>366CA3</color2>
</county>
<county>
 <id>37</id>
 <name>Marathon</name>
 <URL>#</URL>
 <popup>Any text &lt;BR&gt;information</popup>
 <color1>7798BA</color1>
 <color2>366CA3</color2>
</county>
<county>
 <id>38</id>
 <name>Marinette</name>
 <URL>#</URL>
 <popup>Any text &lt;BR&gt;information</popup>
 <color1>7798BA</color1>
 <color2>366CA3</color2>
</county>
<county>
 <id>39</id>
 <name>Marquette</name>
 <URL>#</URL>
 <popup>Any text &lt;BR&gt;information</popup>
 <color1>7798BA</color1>
 <color2>366CA3</color2>
</county>
<county>
 <id>40</id>
 <name>Menominee</name>
 <URL>#</URL>
 <popup>Any text &lt;BR&gt;information</popup>
 <color1>7798BA</color1>
 <color2>366CA3</color2>
</county>
<county>
 <id>41</id>
 <name>Milwaukee</name>
 <URL>#</URL>
 <popup>Any text &lt;BR&gt;information</popup>
 <color1>7798BA</color1>
 <color2>366CA3</color2>
</county>
<county>
 <id>42</id>
 <name>Monroe</name>
 <URL>#</URL>
 <popup>Any text &lt;BR&gt;information</popup>
 <color1>7798BA</color1>
 <color2>366CA3</color2>
</county>
<county>
 <id>43</id>
 <name>Oconto</name>
 <URL>#</URL>
 <popup>Any text &lt;BR&gt;information</popup>
 <color1>7798BA</color1>
 <color2>366CA3</color2>
</county>
<county>
 <id>44</id>
 <name>Oneida</name>
 <URL>#</URL>
 <popup>Any text &lt;BR&gt;information</popup>
 <color1>7798BA</color1>
 <color2>366CA3</color2>
</county>
<county>
 <id>45</id>
 <name>Outagamie</name>
 <URL>#</URL>
 <popup>Any text &lt;BR&gt;information</popup>
 <color1>7798BA</color1>
 <color2>366CA3</color2>
</county>
<county>
 <id>46</id>
 <name>Ozaukee</name>
 <URL>#</URL>
 <popup>Any text &lt;BR&gt;information</popup>
 <color1>7798BA</color1>
 <color2>366CA3</color2>
</county>
<county>
 <id>47</id>
 <name>Pepin</name>
 <URL>#</URL>
 <popup>Any text &lt;BR&gt;information</popup>
 <color1>7798BA</color1>
 <color2>366CA3</color2>
</county>
<county>
 <id>48</id>
 <name>Pierce</name>
 <URL>#</URL>
 <popup>Any text &lt;BR&gt;information</popup>
 <color1>7798BA</color1>
 <color2>366CA3</color2>
</county>
<county>
 <id>49</id>
 <name>Polk</name>
 <URL>#</URL>
 <popup>Any text &lt;BR&gt;information</popup>
 <color1>7798BA</color1>
 <color2>366CA3</color2>
</county>
<county>
 <id>50</id>
 <name>Portage</name>
 <URL>#</URL>
 <popup>Any text &lt;BR&gt;information</popup>
 <color1>7798BA</color1>
 <color2>366CA3</color2>
</county>
<county>
 <id>51</id>
 <name>Price</name>
 <URL>#</URL>
 <popup>Any text &lt;BR&gt;information</popup>
 <color1>7798BA</color1>
 <color2>366CA3</color2>
</county>
<county>
 <id>52</id>
 <name>Racine</name>
 <URL>#</URL>
 <popup>Any text &lt;BR&gt;information</popup>
 <color1>7798BA</color1>
 <color2>366CA3</color2>
</county>
<county>
 <id>53</id>
 <name>Richland</name>
 <URL>#</URL>
 <popup>Any text &lt;BR&gt;information</popup>
 <color1>7798BA</color1>
 <color2>366CA3</color2>
</county>
<county>
 <id>54</id>
 <name>Rock</name>
 <URL>#</URL>
 <popup>Any text &lt;BR&gt;information</popup>
 <color1>7798BA</color1>
 <color2>366CA3</color2>
</county>
<county>
 <id>55</id>
 <name>Rusk</name>
 <URL>#</URL>
 <popup>Any text &lt;BR&gt;information</popup>
 <color1>7798BA</color1>
 <color2>366CA3</color2>
</county>
<county>
 <id>56</id>
 <name>Sauk</name>
 <URL>#</URL>
 <popup>Any text &lt;BR&gt;information</popup>
 <color1>7798BA</color1>
 <color2>366CA3</color2>
</county>
<county>
 <id>57</id>
 <name>Sawyer</name>
 <URL>#</URL>
 <popup>Any text &lt;BR&gt;information</popup>
 <color1>7798BA</color1>
 <color2>366CA3</color2>
</county>
<county>
 <id>58</id>
 <name>Shawano</name>
 <URL>#</URL>
 <popup>Any text &lt;BR&gt;information</popup>
 <color1>7798BA</color1>
 <color2>366CA3</color2>
</county>
<county>
 <id>59</id>
 <name>Sheboygan</name>
 <URL>#</URL>
 <popup>Any text &lt;BR&gt;information</popup>
 <color1>7798BA</color1>
 <color2>366CA3</color2>
</county>
<county>
 <id>60</id>
 <name>St. Croix</name>
 <URL>#</URL>
 <popup>Any text &lt;BR&gt;information</popup>
 <color1>7798BA</color1>
 <color2>366CA3</color2>
</county>
<county>
 <id>61</id>
 <name>Taylor</name>
 <URL>#</URL>
 <popup>Any text &lt;BR&gt;information</popup>
 <color1>7798BA</color1>
 <color2>366CA3</color2>
</county>
<county>
 <id>62</id>
 <name>Trempealeau</name>
 <URL>#</URL>
 <popup>Any text &lt;BR&gt;information</popup>
 <color1>7798BA</color1>
 <color2>366CA3</color2>
</county>
<county>
 <id>63</id>
 <name>Vernon</name>
 <URL>#</URL>
 <popup>Any text &lt;BR&gt;information</popup>
 <color1>7798BA</color1>
 <color2>366CA3</color2>
</county>
<county>
 <id>64</id>
 <name>Vilas</name>
 <URL>#</URL>
 <popup>Any text &lt;BR&gt;information</popup>
 <color1>7798BA</color1>
 <color2>366CA3</color2>
</county>
<county>
 <id>65</id>
 <name>Walworth</name>
 <URL>#</URL>
 <popup>Any text &lt;BR&gt;information</popup>
 <color1>7798BA</color1>
 <color2>366CA3</color2>
</county>
<county>
 <id>66</id>
 <name>Washburn</name>
 <URL>#</URL>
 <popup>Any text &lt;BR&gt;information</popup>
 <color1>7798BA</color1>
 <color2>366CA3</color2>
</county>
<county>
 <id>67</id>
 <name>Washington</name>
 <URL>#</URL>
 <popup>Any text &lt;BR&gt;information</popup>
 <color1>7798BA</color1>
 <color2>366CA3</color2>
</county>
<county>
 <id>68</id>
 <name>Waukesha</name>
 <URL>#</URL>
 <popup>Any text &lt;BR&gt;information</popup>
 <color1>7798BA</color1>
 <color2>366CA3</color2>
</county>
<county>
 <id>69</id>
 <name>Waupaca</name>
 <URL>#</URL>
 <popup>Any text &lt;BR&gt;information</popup>
 <color1>7798BA</color1>
 <color2>366CA3</color2>
</county>
<county>
 <id>70</id>
 <name>Waushara</name>
 <URL>#</URL>
 <popup>Any text &lt;BR&gt;information</popup>
 <color1>7798BA</color1>
 <color2>366CA3</color2>
</county>
<county>
 <id>71</id>
 <name>Winnebago</name>
 <URL>#</URL>
 <popup>Any text &lt;BR&gt;information</popup>
 <color1>7798BA</color1>
 <color2>366CA3</color2>
</county>
<county>
 <id>72</id>
 <name>Wood</name>
 <URL>#</URL>
 <popup>Any text &lt;BR&gt;information</popup>
 <color1>7798BA</color1>
 <color2>366CA3</color2>
</county>
</map>